bella_openapi/__init__.py
bella_openapi/auth_billing.py
bella_openapi/authorize.py
bella_openapi/config.py
bella_openapi/exception.py
bella_openapi/log.py
bella_openapi/openapi_contexvar.py
bella_openapi/schema.py
bella_openapi/bella_trace/__init__.py
bella_openapi/bella_trace/_context.py
bella_openapi/bella_trace/fastapi_interceptor.py
bella_openapi/bella_trace/record_log.py
bella_openapi/bella_trace/trace_requests.py
bella_openapi/console/__init__.py
bella_openapi/console/models.py
bella_openapi/entity/__init__.py
bella_openapi/entity/standard_domtree.py
bella_openapi/middleware/__init__.py
bella_openapi/middleware/context_middleware.py
bella_openapi/worker/__init__.py
bella_openapi/worker/config.py
bella_openapi/worker/models.py
bella_openapi/worker/task_processor.py
bella_openapi/worker/worker.py
bella_openapi-1.0.5.dist-info/LICENSE
bella_openapi-1.0.5.dist-info/METADATA
bella_openapi-1.0.5.dist-info/WHEEL
bella_openapi-1.0.5.dist-info/top_level.txt
bella_openapi-1.0.5.dist-info/RECORD
