Metadata-Version: 2.1
Name: bella-openapi
Version: 1.0.5
Summary: client for openapi service.
Home-page: 
Author: ['tangxiaolong', 'fanqiangwei', 'zhangxiaojia', 'liumin', 'wangyukun']
Author-email: 
Platform: any
Classifier: Programming Language :: Python :: 3.5
License-File: LICENSE
Requires-Dist: httpx <=0.26.0,>=0.10.0
Requires-Dist: Werkzeug ==3.0.1
Requires-Dist: tiktoken >=0.5.0
Requires-Dist: pydantic >=1.10.14
Requires-Dist: fastapi >=0.100.0
